CHANGES.rst
LICENSE.rst
MANIFEST.in
README.rst
setup.cfg
setup.py
examples/server.py
src/inbus/__init__.py
src/inbus/client/__init__.py
src/inbus/client/publisher.py
src/inbus/client/subscriber.py
src/inbus/server/__init__.py
src/inbus/server/broadcaster.py
src/inbus/server/inbus.py
src/inbus/server/inbus_method_observer.py
src/inbus/server/incoming_message_translator.py
src/inbus/server/message_receiver.py
src/inbus/server/message_sender.py
src/inbus/server/outgoing_message_translator.py
src/inbus/server/registry.py
src/inbus/shared/__init__.py
src/inbus/shared/defaults.py
src/inbus/shared/opcode.py
src/inbus_server.egg-info/PKG-INFO
src/inbus_server.egg-info/SOURCES.txt
src/inbus_server.egg-info/dependency_links.txt
src/inbus_server.egg-info/not-zip-safe
src/inbus_server.egg-info/requires.txt
src/inbus_server.egg-info/top_level.txt